jupyter_spaces/__init__.py
jupyter_spaces/errors.py
jupyter_spaces/magics.py
jupyter_spaces/space.py
jupyter_spaces-0.3.0.dist-info/LICENSE.txt
jupyter_spaces-0.3.0.dist-info/METADATA
jupyter_spaces-0.3.0.dist-info/WHEEL
jupyter_spaces-0.3.0.dist-info/top_level.txt
jupyter_spaces-0.3.0.dist-info/RECORD
