Metadata-Version: 2.1
Name: jupyter-spaces
Version: 0.3.0
Summary: Create parallel namespaces in Jupyter Notebooks
Home-page: https://github.com/davidesarra/jupyter_spaces
Author: Davide Sarra
License: MIT
Keywords: jupyter,ipython,magic,extension,namespace
Classifier: Environment :: Console
Classifier: Framework :: IPython
Classifier: Framework :: Jupyter
Classifier: Intended Audience :: Developers
Classifier: Intended Audience :: Science/Research
Classifier: License :: OSI Approved :: MIT License
Classifier: Operating System :: OS Independent
Classifier: Programming Language :: Python :: 3
Classifier: Programming Language :: Python :: 3.6
Classifier: Programming Language :: Python :: 3.7
Classifier: Programming Language :: Python :: 3.8
Classifier: Programming Language :: Python :: 3.9
Classifier: Programming Language :: Python :: 3.10
Requires-Python: ~=3.6
License-File: LICENSE.txt
Requires-Dist: ipython (>=5.0.0)
